zhihu/__init__.py
zhihu/activity.py
zhihu/acttype.py
zhihu/answer.py
zhihu/author.py
zhihu/base.py
zhihu/client.py
zhihu/collection.py
zhihu/column.py
zhihu/comment.py
zhihu/common.py
zhihu/me.py
zhihu/post.py
zhihu/question.py
zhihu/topic.py
zhihu_py3-0.3.23.dist-info/DESCRIPTION.rst
zhihu_py3-0.3.23.dist-info/METADATA
zhihu_py3-0.3.23.dist-info/RECORD
zhihu_py3-0.3.23.dist-info/WHEEL
zhihu_py3-0.3.23.dist-info/metadata.json
zhihu_py3-0.3.23.dist-info/top_level.txt
