Metadata-Version: 2.0
Name: zhihu-py3
Version: 0.3.23
Summary: Zhihu UNOFFICIAL API library in python3, with help of bs4, lxml, requests and html2text.
Home-page: https://github.com/7sDream/zhihu-py3
Author: 7sDream
Author-email: didislover@gmail.com
License: MIT
Download-URL: https://github.com/7sDream/zhihu-py3
Keywords: zhihu,network,spider,html
Platform: UNKNOWN
Classifier: Development Status :: 3 - Alpha
Classifier: Environment :: Web Environment
Classifier: Intended Audience :: Developers
Classifier: License :: OSI Approved :: MIT License
Classifier: Operating System :: OS Independent
Classifier: Programming Language :: Python :: 3
Classifier: Topic :: Internet :: WWW/HTTP
Classifier: Topic :: Software Development :: Libraries :: Python Modules
Requires-Dist: beautifulsoup4
Requires-Dist: html2text
Requires-Dist: requests
Provides-Extra: lxml
Requires-Dist: lxml; extra == 'lxml'
